magnuslib/__init__.py
magnuslib/main.py
magnuslib-0.0.16.dist-info/licenses/LICENSE
magnuslib-0.0.16.dist-info/METADATA
magnuslib-0.0.16.dist-info/WHEEL
magnuslib-0.0.16.dist-info/top_level.txt
magnuslib-0.0.16.dist-info/RECORD
