Metadata-Version: 2.4
Name: magnuslib
Version: 0.0.16
Summary: My_library
Home-page: https://github.com/magnusred1986
Author: sergey_k
Author-email: qwertyz19861@gmail.com
Project-URL: GitHub, https://github.com/magnusred1986
Keywords: my library
Classifier: Programming Language :: Python :: 3.11
Classifier: License :: OSI Approved :: MIT License
Classifier: Operating System :: OS Independent
Requires-Python: >=3.10
License-File: LICENSE
Requires-Dist: pywin32
Requires-Dist: msoffcrypto-tool
Dynamic: author
Dynamic: author-email
Dynamic: classifier
Dynamic: description
Dynamic: description-content-type
Dynamic: home-page
Dynamic: keywords
Dynamic: license-file
Dynamic: project-url
Dynamic: requires-dist
Dynamic: requires-python
Dynamic: summary
